dwcawriter/__init__.py
dwcawriter/archive.py
dwcawriter/table.py
dwcawriter/data/core/dwc_event_2015_05_29.xml
dwcawriter/data/core/dwc_event_2016_06_21.xml
dwcawriter/data/core/dwc_event_2022-02-02.xml
dwcawriter/data/core/dwc_occurrence.xml
dwcawriter/data/core/dwc_occurrence_2015-07-02.xml
dwcawriter/data/core/dwc_occurrence_2020-04-06.xml
dwcawriter/data/core/dwc_occurrence_2020-04-15.xml
dwcawriter/data/core/dwc_occurrence_2020-07-15.xml
dwcawriter/data/core/dwc_occurrence_2022-02-02.xml
dwcawriter/data/core/dwc_taxon.xml
dwcawriter/data/core/dwc_taxon_2015-04-24.xml
dwcawriter/data/core/dwc_taxon_2022-02-02.xml
dwcawriter/data/extension/external.json
dwcawriter/data/extension/ac/audubon.xml
dwcawriter/data/extension/ac/audubon_2020_10_06.xml
dwcawriter/data/extension/dwc/ChronometricAge_2021-03-27.xml
dwcawriter/data/extension/dwc/identification.xml
dwcawriter/data/extension/dwc/identification_history_2022-02-02.xml
dwcawriter/data/extension/dwc/measurements_or_facts.xml
dwcawriter/data/extension/dwc/measurements_or_facts_2022-02-02.xml
dwcawriter/data/extension/dwc/resource_relation.xml
dwcawriter/data/extension/dwc/resource_relation_2018_01_18.xml
dwcawriter/data/extension/dwc/resource_relationship_2022-02-02.xml
dwcawriter/data/extension/eol/media_extension.xml
dwcawriter/data/extension/eol/reference_extension.xml
dwcawriter/data/extension/gbif/1.0/description.xml
dwcawriter/data/extension/gbif/1.0/distribution.xml
dwcawriter/data/extension/gbif/1.0/distribution_2020-07-15.xml
dwcawriter/data/extension/gbif/1.0/distribution_2022-02-02.xml
dwcawriter/data/extension/gbif/1.0/dna_derived_data_2021-07-05.xml
dwcawriter/data/extension/gbif/1.0/dna_derived_data_2022-02-23.xml
dwcawriter/data/extension/gbif/1.0/identifier.xml
dwcawriter/data/extension/gbif/1.0/images.xml
dwcawriter/data/extension/gbif/1.0/multimedia.xml
dwcawriter/data/extension/gbif/1.0/references.xml
dwcawriter/data/extension/gbif/1.0/releve_2016-05-10.xml
dwca_writer-0.2.0.dist-info/METADATA
dwca_writer-0.2.0.dist-info/WHEEL
dwca_writer-0.2.0.dist-info/top_level.txt
dwca_writer-0.2.0.dist-info/RECORD
