Metadata-Version: 2.1
Name: dwca-writer
Version: 0.2.0
Summary: Python package for writing Darwin Core Archives (DwC-A)
Home-page: https://github.com/pieterprovoost/dwca-writer
Author: Pieter Provoost
Author-email: pieterprovoost@gmail.com
License: MIT
